pwasm/__init__.py
pwasm/decoder.py
pwasm/errors.py
pwasm/executor.py
pwasm/opcodes.py
pwasm/py.typed
pwasm/types.py
pwasm-0.1a0.dist-info/WHEEL
pwasm-0.1a0.dist-info/METADATA
pwasm-0.1a0.dist-info/RECORD
