Metadata-Version: 2.4
Name: pwasm
Version: 0.1a0
Summary: A pure Python WebAssembly runtime
Author: Simon Willison
License-Expression: Apache-2.0
Requires-Python: >=3.10
Project-URL: CI, https://github.com/simonw/pwasm/actions
Project-URL: Changelog, https://github.com/simonw/pwasm/releases
Project-URL: Homepage, https://github.com/simonw/pwasm
Project-URL: Issues, https://github.com/simonw/pwasm/issues
